torch_rechub/__init__.py
torch_rechub/types.py
torch_rechub/basic/__init__.py
torch_rechub/basic/activation.py
torch_rechub/basic/callback.py
torch_rechub/basic/features.py
torch_rechub/basic/initializers.py
torch_rechub/basic/layers.py
torch_rechub/basic/loss_func.py
torch_rechub/basic/metaoptimizer.py
torch_rechub/basic/metric.py
torch_rechub/basic/tracking.py
torch_rechub/data/__init__.py
torch_rechub/data/convert.py
torch_rechub/data/dataset.py
torch_rechub/models/__init__.py
torch_rechub/models/generative/__init__.py
torch_rechub/models/generative/hllm.py
torch_rechub/models/generative/hstu.py
torch_rechub/models/matching/__init__.py
torch_rechub/models/matching/comirec.py
torch_rechub/models/matching/dssm.py
torch_rechub/models/matching/dssm_facebook.py
torch_rechub/models/matching/dssm_senet.py
torch_rechub/models/matching/gru4rec.py
torch_rechub/models/matching/mind.py
torch_rechub/models/matching/narm.py
torch_rechub/models/matching/sasrec.py
torch_rechub/models/matching/sine.py
torch_rechub/models/matching/stamp.py
torch_rechub/models/matching/youtube_dnn.py
torch_rechub/models/matching/youtube_sbc.py
torch_rechub/models/multi_task/__init__.py
torch_rechub/models/multi_task/aitm.py
torch_rechub/models/multi_task/esmm.py
torch_rechub/models/multi_task/mmoe.py
torch_rechub/models/multi_task/ple.py
torch_rechub/models/multi_task/shared_bottom.py
torch_rechub/models/ranking/__init__.py
torch_rechub/models/ranking/afm.py
torch_rechub/models/ranking/autoint.py
torch_rechub/models/ranking/bst.py
torch_rechub/models/ranking/dcn.py
torch_rechub/models/ranking/dcn_v2.py
torch_rechub/models/ranking/deepffm.py
torch_rechub/models/ranking/deepfm.py
torch_rechub/models/ranking/dien.py
torch_rechub/models/ranking/din.py
torch_rechub/models/ranking/edcn.py
torch_rechub/models/ranking/fibinet.py
torch_rechub/models/ranking/widedeep.py
torch_rechub/serving/__init__.py
torch_rechub/serving/annoy.py
torch_rechub/serving/base.py
torch_rechub/serving/faiss.py
torch_rechub-0.1.0.dist-info/METADATA
torch_rechub-0.1.0.dist-info/WHEEL
torch_rechub-0.1.0.dist-info/licenses/LICENSE
torch_rechub-0.1.0.dist-info/RECORD
