Metadata-Version: 2.4
Name: torch-rechub
Version: 0.1.0
Summary: A Pytorch Toolbox for Recommendation Models, Easy-to-use and Easy-to-extend.
Project-URL: Homepage, https://github.com/datawhalechina/torch-rechub
Project-URL: Documentation, https://www.torch-rechub.com
Project-URL: Repository, https://github.com/datawhalechina/torch-rechub.git
Project-URL: Issues, https://github.com/datawhalechina/torch-rechub/issues
Author-email: rechub team <morningsky@tju.edu.cn>
License: MIT
License-File: LICENSE
Classifier: Development Status :: 4 - Beta
Classifier: Intended Audience :: Developers
Classifier: Intended Audience :: Science/Research
Classifier: License :: OSI Approved :: MIT License
Classifier: Operating System :: OS Independent
Classifier: Programming Language :: Python :: 3
Classifier: Programming Language :: Python :: 3.9
Classifier: Programming Language :: Python :: 3.10
Classifier: Programming Language :: Python :: 3.11
Classifier: Programming Language :: Python :: 3.12
Classifier: Topic :: Scientific/Engineering :: Artificial Intelligence
Requires-Python: >=3.9
Requires-Dist: accelerate>=1.0.1
Requires-Dist: numpy>=1.19.0
Requires-Dist: pandas>=1.2.0
Requires-Dist: scikit-learn>=0.24.0
Requires-Dist: torch>=1.10.0
Requires-Dist: tqdm>=4.60.0
Requires-Dist: transformers>=4.46.3
Provides-Extra: annoy
Requires-Dist: annoy>=1.17.2; extra == 'annoy'
Provides-Extra: bigdata
Requires-Dist: pyarrow~=21.0; extra == 'bigdata'
Provides-Extra: dev
Requires-Dist: bandit>=1.7.0; extra == 'dev'
Requires-Dist: flake8>=3.8.0; extra == 'dev'
Requires-Dist: isort==5.13.2; extra == 'dev'
Requires-Dist: mypy>=0.800; extra == 'dev'
Requires-Dist: pre-commit>=2.20.0; extra == 'dev'
Requires-Dist: pyarrow-stubs>=20.0; extra == 'dev'
Requires-Dist: pytest-cov>=2.0; extra == 'dev'
Requires-Dist: pytest>=6.0; extra == 'dev'
Requires-Dist: toml>=0.10.2; extra == 'dev'
Requires-Dist: yapf==0.43.0; extra == 'dev'
Provides-Extra: faiss
Requires-Dist: faiss-cpu==1.13.0; extra == 'faiss'
Provides-Extra: milvus
Requires-Dist: pymilvus>=2.6.5; extra == 'milvus'
Provides-Extra: onnx
Requires-Dist: onnx>=1.14.0; extra == 'onnx'
Requires-Dist: onnxconverter-common>=1.14.0; extra == 'onnx'
Requires-Dist: onnxruntime>=1.14.0; extra == 'onnx'
Provides-Extra: tracking
Requires-Dist: swanlab>=0.1.0; extra == 'tracking'
Requires-Dist: tensorboardx>=2.5; extra == 'tracking'
Requires-Dist: wandb>=0.13.0; extra == 'tracking'
Provides-Extra: visualization
Requires-Dist: graphviz>=0.20; extra == 'visualization'
Requires-Dist: torchview>=0.2.6; extra == 'visualization'
